{
  "unversionedId": "custom-logger",
  "id": "custom-logger",
  "isDocsHomePage": false,
  "title": "Custom Logger",
  "description": "The logger is customized using log creators. A log creator is a function which receives a log level and returns a log function. The log function receives namespace, level, label, and log.",
  "source": "@site/..\\docs\\CustomLogger.md",
  "slug": "/custom-logger",
  "permalink": "/docs/next/custom-logger",
  "editUrl": "https://github.com/tulios/kafkajs/edit/master/docs/../docs/CustomLogger.md",
  "version": "current",
  "lastUpdatedBy": "Author",
  "lastUpdatedAt": 1539502055,
  "sidebar": "docs",
  "previous": {
    "title": "Instrumentation Events",
    "permalink": "/docs/next/instrumentation-events"
  },
  "next": {
    "title": "Retry Mechanism Explained",
    "permalink": "/docs/next/retry-detailed"
  }
}